{
  "generatedAt": "2026-07-01",
  "nSims": 50000,
  "completed": 5,
  "players": [
    {
      "name": "Dhody",
      "a": "ARG",
      "b": "CAN",
      "aTeam": {
        "code": "ARG",
        "name": "Argentina",
        "flag": "🇦🇷",
        "elo": 2045
      },
      "bTeam": {
        "code": "CAN",
        "name": "Canada",
        "flag": "🇨🇦",
        "elo": 1795
      },
      "rankProbs": [
        0.32122,
        0.2649,
        0.17336,
        0.09628,
        0.05916,
        0.04074,
        0.02954,
        0.0148
      ],
      "pWin": 0.32122,
      "pTop3": 0.7594799999999999,
      "pBottom3": 0.08507999999999999,
      "expRank": 2.62164,
      "expScore": 6.34488,
      "watch": [
        {
          "matchId": "m85",
          "root": "ALG",
          "vs": "SUI",
          "swing": 0.5025793005425396,
          "winSwing": 0.15418629784550258,
          "rootImprovesRankBy": 0.5025793005425396,
          "rootRaisesWinBy": 0.15418629784550258
        },
        {
          "matchId": "m77",
          "root": "SWE",
          "vs": "FRA",
          "swing": 0.4120051899395145,
          "winSwing": 0.0925795391139182,
          "rootImprovesRankBy": 0.4120051899395145,
          "rootRaisesWinBy": 0.0925795391139182
        },
        {
          "matchId": "m87",
          "root": "GHA",
          "vs": "COL",
          "swing": 0.3564546058498981,
          "winSwing": 0.060435353863388386,
          "rootImprovesRankBy": 0.3564546058498981,
          "rootRaisesWinBy": 0.060435353863388386
        },
        {
          "matchId": "m79",
          "root": "ECU",
          "vs": "MEX",
          "swing": 0.346189634389507,
          "winSwing": 0.05044624288580929,
          "rootImprovesRankBy": 0.346189634389507,
          "rootRaisesWinBy": 0.05044624288580929
        }
      ]
    },
    {
      "name": "Shishu",
      "a": "FRA",
      "b": "SUI",
      "aTeam": {
        "code": "FRA",
        "name": "France",
        "flag": "🇫🇷",
        "elo": 2075
      },
      "bTeam": {
        "code": "SUI",
        "name": "Switzerland",
        "flag": "🇨🇭",
        "elo": 1850
      },
      "rankProbs": [
        0.21372,
        0.15792,
        0.14662,
        0.13252,
        0.10562,
        0.08766,
        0.07522,
        0.08072
      ],
      "pWin": 0.21372,
      "pTop3": 0.5182599999999999,
      "pBottom3": 0.24359999999999998,
      "expRank": 3.72586,
      "expScore": 7.82168,
      "watch": [
        {
          "matchId": "m87",
          "root": "GHA",
          "vs": "COL",
          "swing": 0.40358864334404876,
          "winSwing": 0.0471797969173158,
          "rootImprovesRankBy": 0.40358864334404876,
          "rootRaisesWinBy": 0.0471797969173158
        },
        {
          "matchId": "m86",
          "root": "CPV",
          "vs": "ARG",
          "swing": 0.3452556669510871,
          "winSwing": 0.06503059125579189,
          "rootImprovesRankBy": 0.3452556669510871,
          "rootRaisesWinBy": 0.06503059125579189
        },
        {
          "matchId": "m79",
          "root": "ECU",
          "vs": "MEX",
          "swing": 0.3079237815527458,
          "winSwing": 0.021797545468451,
          "rootImprovesRankBy": 0.3079237815527458,
          "rootRaisesWinBy": 0.021797545468451
        },
        {
          "matchId": "m83",
          "root": "AUT",
          "vs": "ESP",
          "swing": 0.17224375222965627,
          "winSwing": 0.022961280553843028,
          "rootImprovesRankBy": 0.17224375222965627,
          "rootRaisesWinBy": 0.022961280553843028
        }
      ]
    },
    {
      "name": "Misra",
      "a": "ESP",
      "b": "SEN",
      "aTeam": {
        "code": "ESP",
        "name": "Spain",
        "flag": "🇪🇸",
        "elo": 2055
      },
      "bTeam": {
        "code": "SEN",
        "name": "Senegal",
        "flag": "🇸🇳",
        "elo": 1865
      },
      "rankProbs": [
        0.12774,
        0.1138,
        0.10442,
        0.1177,
        0.12122,
        0.11822,
        0.12754,
        0.16936
      ],
      "pWin": 0.12774,
      "pTop3": 0.34596,
      "pBottom3": 0.41512,
      "expRank": 4.70248,
      "expScore": 9.38758,
      "watch": [
        {
          "matchId": "m84",
          "root": "CRO",
          "vs": "POR",
          "swing": 0.4726062077930635,
          "winSwing": 0.03915119628739111,
          "rootImprovesRankBy": 0.4726062077930635,
          "rootRaisesWinBy": 0.03915119628739111
        },
        {
          "matchId": "m86",
          "root": "CPV",
          "vs": "ARG",
          "swing": 0.43668563211490685,
          "winSwing": 0.059274701442357774,
          "rootImprovesRankBy": 0.43668563211490685,
          "rootRaisesWinBy": 0.059274701442357774
        },
        {
          "matchId": "m81",
          "root": "BIH",
          "vs": "USA",
          "swing": 0.43554626607414537,
          "winSwing": 0.03173127654398941,
          "rootImprovesRankBy": 0.43554626607414537,
          "rootRaisesWinBy": 0.03173127654398941
        },
        {
          "matchId": "m77",
          "root": "SWE",
          "vs": "FRA",
          "swing": 0.3844066494888807,
          "winSwing": 0.035316122402776914,
          "rootImprovesRankBy": 0.3844066494888807,
          "rootRaisesWinBy": 0.035316122402776914
        }
      ]
    },
    {
      "name": "Mad",
      "a": "ENG",
      "b": "MEX",
      "aTeam": {
        "code": "ENG",
        "name": "England",
        "flag": "🏴󠁧󠁢󠁥󠁮󠁧󠁿",
        "elo": 2005
      },
      "bTeam": {
        "code": "MEX",
        "name": "Mexico",
        "flag": "🇲🇽",
        "elo": 1895
      },
      "rankProbs": [
        0.07012,
        0.1466,
        0.18712,
        0.16426,
        0.1233,
        0.0972,
        0.09788,
        0.11352
      ],
      "pWin": 0.07012,
      "pTop3": 0.40384000000000003,
      "pBottom3": 0.3086,
      "expRank": 4.37474,
      "expScore": 8.9842,
      "watch": [
        {
          "matchId": "m86",
          "root": "CPV",
          "vs": "ARG",
          "swing": 0.5097555739262964,
          "winSwing": 0.05258566147346992,
          "rootImprovesRankBy": 0.5097555739262964,
          "rootRaisesWinBy": 0.05258566147346992
        },
        {
          "matchId": "m85",
          "root": "ALG",
          "vs": "SUI",
          "swing": 0.3755220457488564,
          "winSwing": 0.04870259343575651,
          "rootImprovesRankBy": 0.3755220457488564,
          "rootRaisesWinBy": 0.04870259343575651
        },
        {
          "matchId": "m87",
          "root": "GHA",
          "vs": "COL",
          "swing": 0.3461382541620486,
          "winSwing": 0.017289449063477028,
          "rootImprovesRankBy": 0.3461382541620486,
          "rootRaisesWinBy": 0.017289449063477028
        },
        {
          "matchId": "m77",
          "root": "SWE",
          "vs": "FRA",
          "swing": 0.3363866647828253,
          "winSwing": 0.02781403504458231,
          "rootImprovesRankBy": 0.3363866647828253,
          "rootRaisesWinBy": 0.02781403504458231
        }
      ]
    },
    {
      "name": "Kuks",
      "a": "NED",
      "b": "NOR",
      "aTeam": {
        "code": "NED",
        "name": "Netherlands",
        "flag": "🇳🇱",
        "elo": 1960
      },
      "bTeam": {
        "code": "NOR",
        "name": "Norway",
        "flag": "🇳🇴",
        "elo": 1840
      },
      "rankProbs": [
        0.00258,
        0.02406,
        0.0774,
        0.15086,
        0.2209,
        0.2464,
        0.19606,
        0.08174
      ],
      "pWin": 0.00258,
      "pTop3": 0.10404,
      "pBottom3": 0.5242,
      "expRank": 5.49558,
      "expScore": 10.31366,
      "watch": [
        {
          "matchId": "m86",
          "root": "CPV",
          "vs": "ARG",
          "swing": 0.6524330717946691,
          "winSwing": 0.011716579278353696,
          "rootImprovesRankBy": 0.6524330717946691,
          "rootRaisesWinBy": 0.011716579278353696
        },
        {
          "matchId": "m81",
          "root": "BIH",
          "vs": "USA",
          "swing": 0.6465018087627463,
          "winSwing": 0.0019458001958869314,
          "rootImprovesRankBy": 0.6465018087627463,
          "rootRaisesWinBy": 0.0019458001958869314
        },
        {
          "matchId": "m84",
          "root": "CRO",
          "vs": "POR",
          "swing": 0.6089910388599105,
          "winSwing": 0.004271057033039236,
          "rootImprovesRankBy": 0.6089910388599105,
          "rootRaisesWinBy": 0.004271057033039236
        },
        {
          "matchId": "m83",
          "root": "AUT",
          "vs": "ESP",
          "swing": 0.5966500232409278,
          "winSwing": 0.005201763456378633,
          "rootImprovesRankBy": 0.5966500232409278,
          "rootRaisesWinBy": 0.005201763456378633
        }
      ]
    },
    {
      "name": "Shri",
      "a": "BRA",
      "b": "BEL",
      "aTeam": {
        "code": "BRA",
        "name": "Brazil",
        "flag": "🇧🇷",
        "elo": 2000
      },
      "bTeam": {
        "code": "BEL",
        "name": "Belgium",
        "flag": "🇧🇪",
        "elo": 1895
      },
      "rankProbs": [
        0.17024,
        0.16324,
        0.1236,
        0.11574,
        0.1191,
        0.11684,
        0.11296,
        0.07828
      ],
      "pWin": 0.17024,
      "pTop3": 0.45708,
      "pBottom3": 0.30808,
      "expRank": 4.04398,
      "expScore": 8.25686,
      "watch": [
        {
          "matchId": "m86",
          "root": "CPV",
          "vs": "ARG",
          "swing": 0.5164889496019485,
          "winSwing": 0.08524698616481549,
          "rootImprovesRankBy": 0.5164889496019485,
          "rootRaisesWinBy": 0.08524698616481549
        },
        {
          "matchId": "m81",
          "root": "BIH",
          "vs": "USA",
          "swing": 0.4183471582856164,
          "winSwing": 0.036944151614444226,
          "rootImprovesRankBy": 0.4183471582856164,
          "rootRaisesWinBy": 0.036944151614444226
        },
        {
          "matchId": "m77",
          "root": "SWE",
          "vs": "FRA",
          "swing": 0.40883397262184173,
          "winSwing": 0.0550433415074458,
          "rootImprovesRankBy": 0.40883397262184173,
          "rootRaisesWinBy": 0.0550433415074458
        },
        {
          "matchId": "m80",
          "root": "COD",
          "vs": "ENG",
          "swing": 0.3984979874528567,
          "winSwing": 0.03678613987402585,
          "rootImprovesRankBy": 0.3984979874528567,
          "rootRaisesWinBy": 0.03678613987402585
        }
      ]
    },
    {
      "name": "Anuj",
      "a": "USA",
      "b": "GER",
      "aTeam": {
        "code": "USA",
        "name": "USA",
        "flag": "🇺🇸",
        "elo": 1925
      },
      "bTeam": {
        "code": "GER",
        "name": "Germany",
        "flag": "🇩🇪",
        "elo": 1970
      },
      "rankProbs": [
        0.00442,
        0.02782,
        0.058,
        0.0872,
        0.1289,
        0.18542,
        0.237,
        0.27124
      ],
      "pWin": 0.00442,
      "pTop3": 0.09024000000000001,
      "pBottom3": 0.6936599999999999,
      "expRank": 6.1688,
      "expScore": 11.27368,
      "watch": [
        {
          "matchId": "m87",
          "root": "GHA",
          "vs": "COL",
          "swing": 0.595447588856163,
          "winSwing": 0.0031831862540753187,
          "rootImprovesRankBy": 0.595447588856163,
          "rootRaisesWinBy": 0.0031831862540753187
        },
        {
          "matchId": "m77",
          "root": "SWE",
          "vs": "FRA",
          "swing": 0.5565055511429025,
          "winSwing": 0.0010702039909026191,
          "rootImprovesRankBy": 0.5565055511429025,
          "rootRaisesWinBy": 0.0010702039909026191
        },
        {
          "matchId": "m79",
          "root": "ECU",
          "vs": "MEX",
          "swing": 0.5355205109125096,
          "winSwing": 0.005383665812826279,
          "rootImprovesRankBy": 0.5355205109125096,
          "rootRaisesWinBy": 0.005383665812826279
        },
        {
          "matchId": "m86",
          "root": "CPV",
          "vs": "ARG",
          "swing": 0.45996405485438174,
          "winSwing": 0.007064041381825981,
          "rootImprovesRankBy": 0.45996405485438174,
          "rootRaisesWinBy": 0.007064041381825981
        }
      ]
    },
    {
      "name": "Dhirani",
      "a": "POR",
      "b": "COL",
      "aTeam": {
        "code": "POR",
        "name": "Portugal",
        "flag": "🇵🇹",
        "elo": 1975
      },
      "bTeam": {
        "code": "COL",
        "name": "Colombia",
        "flag": "🇨🇴",
        "elo": 1875
      },
      "rankProbs": [
        0.08996,
        0.10166,
        0.12948,
        0.13544,
        0.1218,
        0.10752,
        0.1238,
        0.19034
      ],
      "pWin": 0.08996,
      "pTop3": 0.32110000000000005,
      "pBottom3": 0.42166000000000003,
      "expRank": 4.86692,
      "expScore": 9.61746,
      "watch": [
        {
          "matchId": "m83",
          "root": "AUT",
          "vs": "ESP",
          "swing": 0.6584711506732113,
          "winSwing": 0.07157982419869946,
          "rootImprovesRankBy": 0.6584711506732113,
          "rootRaisesWinBy": 0.07157982419869946
        },
        {
          "matchId": "m86",
          "root": "CPV",
          "vs": "ARG",
          "swing": 0.49803746714727914,
          "winSwing": 0.06963127050478704,
          "rootImprovesRankBy": 0.49803746714727914,
          "rootRaisesWinBy": 0.06963127050478704
        },
        {
          "matchId": "m77",
          "root": "SWE",
          "vs": "FRA",
          "swing": 0.4505200200927808,
          "winSwing": 0.029084884471669015,
          "rootImprovesRankBy": 0.4505200200927808,
          "rootRaisesWinBy": 0.029084884471669015
        },
        {
          "matchId": "m85",
          "root": "ALG",
          "vs": "SUI",
          "swing": 0.38593241182926175,
          "winSwing": 0.03391212509260649,
          "rootImprovesRankBy": 0.38593241182926175,
          "rootRaisesWinBy": 0.03391212509260649
        }
      ]
    }
  ],
  "groups": {
    "A": [
      {
        "code": "ARG",
        "name": "Argentina",
        "flag": "🇦🇷",
        "posProbs": [
          0.22142,
          0.20904,
          0.19236,
          0.13912,
          0.08526,
          0.0623,
          0.04244,
          0.04806
        ],
        "reach": {
          "R16": 0.90768,
          "QF": 0.74238,
          "SF": 0.57652,
          "F": 0.3521,
          "win": 0.19594
        },
        "status": {
          "alive": true
        }
      },
      {
        "code": "FRA",
        "name": "France",
        "flag": "🇫🇷",
        "posProbs": [
          0.268,
          0.1942,
          0.17702,
          0.11864,
          0.06454,
          0.04928,
          0.04868,
          0.07964
        ],
        "reach": {
          "R16": 0.85762,
          "QF": 0.75192,
          "SF": 0.60282,
          "F": 0.38706,
          "win": 0.2445
        },
        "status": {
          "alive": true
        }
      },
      {
        "code": "ESP",
        "name": "Spain",
        "flag": "🇪🇸",
        "posProbs": [
          0.16586,
          0.14048,
          0.1347,
          0.11758,
          0.11646,
          0.1259,
          0.10328,
          0.09574
        ],
        "reach": {
          "R16": 0.82542,
          "QF": 0.55194,
          "SF": 0.4048,
          "F": 0.24288,
          "win": 0.14652
        },
        "status": {
          "alive": true
        }
      },
      {
        "code": "ENG",
        "name": "England",
        "flag": "🏴󠁧󠁢󠁥󠁮󠁧󠁿",
        "posProbs": [
          0.11036,
          0.13204,
          0.13176,
          0.16372,
          0.1776,
          0.11732,
          0.07378,
          0.09342
        ],
        "reach": {
          "R16": 0.8316,
          "QF": 0.5745,
          "SF": 0.3253,
          "F": 0.18478,
          "win": 0.09206
        },
        "status": {
          "alive": true
        }
      },
      {
        "code": "NED",
        "name": "Netherlands",
        "flag": "🇳🇱",
        "posProbs": [
          0,
          0,
          0.00038,
          0.00816,
          0.05676,
          0.20746,
          0.40834,
          0.3189
        ],
        "reach": {
          "R16": 0,
          "QF": 0,
          "SF": 0,
          "F": 0,
          "win": 0
        },
        "status": {
          "alive": false,
          "round": "R32"
        }
      },
      {
        "code": "BRA",
        "name": "Brazil",
        "flag": "🇧🇷",
        "posProbs": [
          0.1385,
          0.1783,
          0.18144,
          0.20706,
          0.18152,
          0.09104,
          0.02214,
          0
        ],
        "reach": {
          "R16": 1,
          "QF": 0.72368,
          "SF": 0.4197,
          "F": 0.23458,
          "win": 0.11398
        },
        "status": {
          "alive": true
        }
      },
      {
        "code": "USA",
        "name": "USA",
        "flag": "🇺🇸",
        "posProbs": [
          0.03946,
          0.0707,
          0.0972,
          0.15322,
          0.19474,
          0.1643,
          0.11904,
          0.16134
        ],
        "reach": {
          "R16": 0.72426,
          "QF": 0.412,
          "SF": 0.16232,
          "F": 0.07042,
          "win": 0.02838
        },
        "status": {
          "alive": true
        }
      },
      {
        "code": "POR",
        "name": "Portugal",
        "flag": "🇵🇹",
        "posProbs": [
          0.0564,
          0.07524,
          0.08514,
          0.0925,
          0.12312,
          0.1824,
          0.1823,
          0.2029
        ],
        "reach": {
          "R16": 0.66894,
          "QF": 0.29676,
          "SF": 0.18298,
          "F": 0.09034,
          "win": 0.04404
        },
        "status": {
          "alive": true
        }
      }
    ],
    "B": [
      {
        "code": "CAN",
        "name": "Canada",
        "flag": "🇨🇦",
        "posProbs": [
          0.14712,
          0.21718,
          0.24614,
          0.21602,
          0.13506,
          0.03848,
          0,
          0
        ],
        "reach": {
          "R16": 1,
          "QF": 0.381,
          "SF": 0.09082,
          "F": 0.02346,
          "win": 0.00598
        },
        "status": {
          "alive": true
        }
      },
      {
        "code": "SUI",
        "name": "Switzerland",
        "flag": "🇨🇭",
        "posProbs": [
          0.15612,
          0.1244,
          0.09722,
          0.0994,
          0.11474,
          0.11458,
          0.14028,
          0.15326
        ],
        "reach": {
          "R16": 0.58632,
          "QF": 0.30304,
          "SF": 0.0996,
          "F": 0.03384,
          "win": 0.00992
        },
        "status": {
          "alive": true
        }
      },
      {
        "code": "SEN",
        "name": "Senegal",
        "flag": "🇸🇳",
        "posProbs": [
          0.10328,
          0.11112,
          0.10148,
          0.08524,
          0.06868,
          0.08006,
          0.15604,
          0.2941
        ],
        "reach": {
          "R16": 0.45872,
          "QF": 0.21554,
          "SF": 0.0664,
          "F": 0.02254,
          "win": 0.0074
        },
        "status": {
          "alive": true
        }
      },
      {
        "code": "MEX",
        "name": "Mexico",
        "flag": "🇲🇽",
        "posProbs": [
          0.12074,
          0.10958,
          0.1095,
          0.12172,
          0.12652,
          0.11806,
          0.14342,
          0.15046
        ],
        "reach": {
          "R16": 0.58898,
          "QF": 0.23866,
          "SF": 0.09988,
          "F": 0.042,
          "win": 0.01478
        },
        "status": {
          "alive": true
        }
      },
      {
        "code": "NOR",
        "name": "Norway",
        "flag": "🇳🇴",
        "posProbs": [
          0.13264,
          0.16304,
          0.22382,
          0.24822,
          0.175,
          0.05728,
          0,
          0
        ],
        "reach": {
          "R16": 1,
          "QF": 0.27632,
          "SF": 0.0991,
          "F": 0.03412,
          "win": 0.00932
        },
        "status": {
          "alive": true
        }
      },
      {
        "code": "BEL",
        "name": "Belgium",
        "flag": "🇧🇪",
        "posProbs": [
          0.14336,
          0.13196,
          0.11318,
          0.09378,
          0.06696,
          0.07328,
          0.13588,
          0.2416
        ],
        "reach": {
          "R16": 0.54128,
          "QF": 0.28048,
          "SF": 0.0996,
          "F": 0.03826,
          "win": 0.01504
        },
        "status": {
          "alive": true
        }
      },
      {
        "code": "GER",
        "name": "Germany",
        "flag": "🇩🇪",
        "posProbs": [
          0,
          0,
          0,
          0.03392,
          0.20748,
          0.41676,
          0.30352,
          0.03832
        ],
        "reach": {
          "R16": 0,
          "QF": 0,
          "SF": 0,
          "F": 0,
          "win": 0
        },
        "status": {
          "alive": false,
          "round": "R32"
        }
      },
      {
        "code": "COL",
        "name": "Colombia",
        "flag": "🇨🇴",
        "posProbs": [
          0.19674,
          0.14272,
          0.10866,
          0.1017,
          0.10556,
          0.1015,
          0.12086,
          0.12226
        ],
        "reach": {
          "R16": 0.64462,
          "QF": 0.36712,
          "SF": 0.1326,
          "F": 0.05034,
          "win": 0.01574
        },
        "status": {
          "alive": true
        }
      }
    ]
  },
  "watchMeta": [
    {
      "matchId": "m77",
      "round": "R32",
      "home": {
        "code": "FRA",
        "name": "France",
        "flag": "🇫🇷",
        "elo": 2075
      },
      "away": {
        "code": "SWE",
        "name": "Sweden",
        "flag": "🇸🇪",
        "elo": 1795
      }
    },
    {
      "matchId": "m79",
      "round": "R32",
      "home": {
        "code": "MEX",
        "name": "Mexico",
        "flag": "🇲🇽",
        "elo": 1895
      },
      "away": {
        "code": "ECU",
        "name": "Ecuador",
        "flag": "🇪🇨",
        "elo": 1835
      }
    },
    {
      "matchId": "m80",
      "round": "R32",
      "home": {
        "code": "ENG",
        "name": "England",
        "flag": "🏴󠁧󠁢󠁥󠁮󠁧󠁿",
        "elo": 2005
      },
      "away": {
        "code": "COD",
        "name": "DR Congo",
        "flag": "🇨🇩",
        "elo": 1750
      }
    },
    {
      "matchId": "m81",
      "round": "R32",
      "home": {
        "code": "USA",
        "name": "USA",
        "flag": "🇺🇸",
        "elo": 1925
      },
      "away": {
        "code": "BIH",
        "name": "Bosnia",
        "flag": "🇧🇦",
        "elo": 1765
      }
    },
    {
      "matchId": "m82",
      "round": "R32",
      "home": {
        "code": "BEL",
        "name": "Belgium",
        "flag": "🇧🇪",
        "elo": 1895
      },
      "away": {
        "code": "SEN",
        "name": "Senegal",
        "flag": "🇸🇳",
        "elo": 1865
      }
    },
    {
      "matchId": "m83",
      "round": "R32",
      "home": {
        "code": "ESP",
        "name": "Spain",
        "flag": "🇪🇸",
        "elo": 2055
      },
      "away": {
        "code": "AUT",
        "name": "Austria",
        "flag": "🇦🇹",
        "elo": 1805
      }
    },
    {
      "matchId": "m84",
      "round": "R32",
      "home": {
        "code": "POR",
        "name": "Portugal",
        "flag": "🇵🇹",
        "elo": 1975
      },
      "away": {
        "code": "CRO",
        "name": "Croatia",
        "flag": "🇭🇷",
        "elo": 1855
      }
    },
    {
      "matchId": "m85",
      "round": "R32",
      "home": {
        "code": "SUI",
        "name": "Switzerland",
        "flag": "🇨🇭",
        "elo": 1850
      },
      "away": {
        "code": "ALG",
        "name": "Algeria",
        "flag": "🇩🇿",
        "elo": 1790
      }
    },
    {
      "matchId": "m86",
      "round": "R32",
      "home": {
        "code": "ARG",
        "name": "Argentina",
        "flag": "🇦🇷",
        "elo": 2045
      },
      "away": {
        "code": "CPV",
        "name": "Cape Verde",
        "flag": "🇨🇻",
        "elo": 1700
      }
    },
    {
      "matchId": "m87",
      "round": "R32",
      "home": {
        "code": "COL",
        "name": "Colombia",
        "flag": "🇨🇴",
        "elo": 1875
      },
      "away": {
        "code": "GHA",
        "name": "Ghana",
        "flag": "🇬🇭",
        "elo": 1775
      }
    },
    {
      "matchId": "m88",
      "round": "R32",
      "home": {
        "code": "AUS",
        "name": "Australia",
        "flag": "🇦🇺",
        "elo": 1770
      },
      "away": {
        "code": "EGY",
        "name": "Egypt",
        "flag": "🇪🇬",
        "elo": 1825
      }
    },
    {
      "matchId": "m90",
      "round": "R16",
      "home": {
        "code": "CAN",
        "name": "Canada",
        "flag": "🇨🇦",
        "elo": 1795
      },
      "away": {
        "code": "MAR",
        "name": "Morocco",
        "flag": "🇲🇦",
        "elo": 1875
      }
    },
    {
      "matchId": "m91",
      "round": "R16",
      "home": {
        "code": "BRA",
        "name": "Brazil",
        "flag": "🇧🇷",
        "elo": 2000
      },
      "away": {
        "code": "NOR",
        "name": "Norway",
        "flag": "🇳🇴",
        "elo": 1840
      }
    }
  ],
  "history": [
    {
      "at": "2026-06-29",
      "completed": 1,
      "pWin": {
        "Dhody": 26.9,
        "Shishu": 16.7,
        "Misra": 11.6,
        "Mad": 6.3,
        "Kuks": 6.4,
        "Shri": 11.8,
        "Anuj": 11.3,
        "Dhirani": 9
      },
      "expRank": {
        "Dhody": 2.93,
        "Shishu": 4.18,
        "Misra": 4.75,
        "Mad": 4.42,
        "Kuks": 5.38,
        "Shri": 4.81,
        "Anuj": 4.61,
        "Dhirani": 4.91
      }
    },
    {
      "at": "2026-06-30",
      "completed": 4,
      "pWin": {
        "Dhody": 32.3,
        "Shishu": 21.3,
        "Misra": 12.6,
        "Mad": 7,
        "Kuks": 0.1,
        "Shri": 17.4,
        "Anuj": 0.6,
        "Dhirani": 8.7
      },
      "expRank": {
        "Dhody": 2.56,
        "Shishu": 3.65,
        "Misra": 4.59,
        "Mad": 4.3,
        "Kuks": 6.41,
        "Shri": 3.88,
        "Anuj": 5.85,
        "Dhirani": 4.76
      }
    },
    {
      "at": "2026-07-01",
      "completed": 5,
      "pWin": {
        "Dhody": 32.1,
        "Shishu": 21.4,
        "Misra": 12.8,
        "Mad": 7,
        "Kuks": 0.3,
        "Shri": 17,
        "Anuj": 0.4,
        "Dhirani": 9
      },
      "expRank": {
        "Dhody": 2.62,
        "Shishu": 3.73,
        "Misra": 4.7,
        "Mad": 4.37,
        "Kuks": 5.5,
        "Shri": 4.04,
        "Anuj": 6.17,
        "Dhirani": 4.87
      }
    }
  ]
}